fastapi_g_context/__init__.py
fastapi_g_context/fastapi_g.py
fastapi_g_context-0.0.2.dist-info/LICENSE
fastapi_g_context-0.0.2.dist-info/METADATA
fastapi_g_context-0.0.2.dist-info/WHEEL
fastapi_g_context-0.0.2.dist-info/top_level.txt
fastapi_g_context-0.0.2.dist-info/RECORD
