Metadata-Version: 2.1
Name: fastapi-g-context
Version: 0.0.2
Summary: fastapi-g-context is a Python module that provides a simple mechanism for managing     global variables with context isolation in FastAPI applications.         It is designed to ensure that each request operates within its own isolated context,             preventing data leakage between requests.
Home-page: https://github.com/chrisK824/fastapi-g-context
Author: Chris Karvouniaris
Author-email: christos.karvouniaris247@gmail.com
License: MIT
Classifier: Programming Language :: Python :: 3
Classifier: Operating System :: OS Independent
Requires-Python: >=3.8
License-File: LICENSE
Requires-Dist: starlette
